[
  {
    "id": "1940593",
    "name": "Session 2 Sports - Fall 2024",
    "date": "Sat Oct 19 2024 08:00:00 GMT-0600 (Mountain Daylight Time)",
    "category": "Sports",
    "location": "Online Event",
    "building": "online event",
    "image": "https://static7.campusgroups.com/upload/byui/2024/r2_image_upload_2467568_Screenshot_20240523_at_90443PM_5232350.png",
    "rsvp": "/rsvp_boot?id=1940593",
    "info": "Session 2 Sports - Fall 2024. Sat Oct 19 2024 08:00 AM - 08:00 PM. Online Event."
  },
  {
    "id": "1933252",
    "name": "Animal Shelter",
    "date": "Sat Oct 19 2024 10:00:00 GMT-0600 (Mountain Daylight Time)",
    "category": "Service",
    "location": "IF Animal Shelter, Off-Campus, Off Campus",
    "building": "if animal shelter",
    "image": "https://static7.campusgroups.com/upload/byui/2024/r2_image_upload_3997750_220305_AnimalShelter_002jpg_101512112.jpeg",
    "rsvp": "/rsvp_boot?id=1933252",
    "info": "Animal Shelter. Sat Oct 19 2024 10:00 AM - 12:30 PM. IF Animal Shelter, Off-Campus, Off Campus."
  },
  {
    "id": "1939061",
    "name": "Canoe and Picnic",
    "date": "Sat Oct 19 2024 10:00:00 GMT-0600 (Mountain Daylight Time)",
    "category": "Outdoor",
    "location": "Warm Slough, Off-Campus, Off Campus",
    "building": "warm slough",
    "image": "https://static7.campusgroups.com/upload/byui/2023/r2_image_upload_3997750_090911canoetrip013jpg_911155323.jpeg",
    "rsvp": "/rsvp_boot?id=1939061",
    "info": "Canoe and Picnic. Sat Oct 19 2024 10:00 AM - 02:00 PM. Warm Slough, Off-Campus, Off Campus."
  },
  {
    "id": "1939649",
    "name": "Lacrosse",
    "date": "Sat Oct 19 2024 10:00:00 GMT-0600 (Mountain Daylight Time)",
    "category": "Sports",
    "location": "Fields, Sports Complex Fields 5-6",
    "building": "fields",
    "image": "https://static7.campusgroups.com/upload/byui/2024/r2_image_upload_3997750_image_upload_3997750_laCrossejpg_417114946_911165437.jpeg",
    "rsvp": "/rsvp_boot?id=1939649",
    "info": "Lacrosse. Sat Oct 19 2024 10:00 AM - 12:00 PM. Fields, Sports Complex Fields 5-6."
  },
  {
    "id": "1939678",
    "name": "Floor Hockey",
    "date": "Sat Oct 19 2024 10:00:00 GMT-0600 (Mountain Daylight Time)",
    "category": "Sports",
    "location": "BYU-Idaho Center, Court 10",
    "building": "center",
    "image": "https://static7.campusgroups.com/upload/byui/2024/r2_image_upload_3372089_flyer_image_upload_3997750_floor_hockeyjpg_828121844_328123924.png",
    "rsvp": "/rsvp_boot?id=1939678",
    "info": "Floor Hockey. Sat Oct 19 2024 10:00 AM - 12:00 PM. BYU-Idaho Center, Court 10."
  },
  {
    "id": "1940225",
    "name": "Fitness: Cycling",
    "date": "Sat Oct 19 2024 10:00:00 GMT-0600 (Mountain Daylight Time)",
    "category": "Fitness/Wellness",
    "location": "Hart, 188 Spin Room",
    "building": "hart",
    "image": "https://static7.campusgroups.com/upload/byui/2023/r2_image_upload_3997750_221116_CyclingClass_018jpg_714102751.jpeg",
    "rsvp": "/rsvp_boot?id=1940225",
    "info": "Fitness: Cycling. Sat Oct 19 2024 10:00 AM - 10:50 AM. Hart, 188 Spin Room."
  },
  {
    "id": "1940321",
    "name": "Brothers In Art: The Parsons",
    "date": "Sat Oct 19 2024 10:00:00 GMT-0600 (Mountain Daylight Time)",
    "category": "Exhibit",
    "location": "Spori Art Gallery",
    "building": "spori",
    "image": "https://static7.campusgroups.com/upload/byui/2024/r2_image_upload_3997750_3d150f7072844c76838b387b30923f6fjpg_924133218.jpeg",
    "rsvp": "/rsvp_boot?id=1940321",
    "info": "Brothers In Art: The Parsons. Sat Oct 19 2024 10:00 AM - 11:00 AM. Spori Art Gallery."
  },
  {
    "id": "1938736",
    "name": "Afternoon Open Registration",
    "date": "Sat Oct 19 2024 12:00:00 GMT-0600 (Mountain Daylight Time)",
    "category": "Outdoor",
    "location": "Ropes Course, Combo of Ropes Course",
    "building": "ropes course",
    "image": "https://static7.campusgroups.com/upload/byui/2021/r2_image_1415142_Ropes_Course_Web_Image_9ddcdc79-d4fe-40b5-99e1-98026befd6aa_7118500.jpg",
    "rsvp": "/rsvp_boot?id=1938736",
    "info": "Afternoon Open Registration. Sat Oct 19 2024 12:00 PM - 08:00 PM. Ropes Course, Combo of Ropes Course."
  },
  {
    "id": "1938852",
    "name": "BYU-I Try a Tri TRYathlon",
    "date": "Sat Oct 19 2024 14:00:00 GMT-0600 (Mountain Daylight Time)",
    "category": "Fitness/Wellness",
    "location": "Fields, Stadium Field and Track, Hart, 215 Swimming Pool (combined lanes)",
    "building": "fields",
    "image": "https://static7.campusgroups.com/upload/byui/2024/r2_image_upload_3997750_Try_a_Tri_IBelong_Calendar_Ad_S24_1_1_002jpg_517101824.jpeg",
    "rsvp": "/rsvp_boot?id=1938852",
    "info": "BYU-I Try a Tri TRYathlon. Sat Oct 19 2024 02:00 PM - 06:00 PM. Fields, Stadium Field and Track, Hart, 215 Swimming Pool (combined lanes)."
  },
  {
    "id": "1939662",
    "name": "Cricket",
    "date": "Sat Oct 19 2024 15:00:00 GMT-0600 (Mountain Daylight Time)",
    "category": "Sports",
    "location": "Fields, Sports Complex Fields 5-6",
    "building": "fields",
    "image": "https://static7.campusgroups.com/upload/byui/2023/r2_image_upload_3997750_cricketjpg_91318145.jpeg",
    "rsvp": "/rsvp_boot?id=1939662",
    "info": "Cricket. Sat Oct 19 2024 03:00 PM - 05:30 PM. Fields, Sports Complex Fields 5-6."
  },
  {
    "id": "1938447",
    "name": "ChoirFest",
    "date": "Sat Oct 19 2024 16:00:00 GMT-0600 (Mountain Daylight Time)",
    "category": "Performing/Visual Arts",
    "location": "Snow, 136 Barrus Concert Hall",
    "building": "snow",
    "image": "https://static7.campusgroups.com/upload/byui/2024/r2_image_upload_3997750_Choirfest_IBelong01_10714352.png",
    "rsvp": "/rsvp_boot?id=1938447",
    "info": "ChoirFest. Sat Oct 19 2024 04:00 PM - 05:30 PM. Snow, 136 Barrus Concert Hall."
  },
  {
    "id": "1940119",
    "name": "Table Tennis Tournament",
    "date": "Sat Oct 19 2024 17:00:00 GMT-0600 (Mountain Daylight Time)",
    "category": "Sports",
    "location": "Hart, 161A Wrestling Room",
    "building": "hart",
    "image": "https://static7.campusgroups.com/upload/byui/2024/r2_image_upload_3997750_table_tennis_spring_21_jpg_202209151433_101453143.jpeg",
    "rsvp": "/rsvp_boot?id=1940119",
    "info": "Table Tennis Tournament. Sat Oct 19 2024 05:00 PM - 07:30 PM. Hart, 161A Wrestling Room."
  },
{
  "id": "1932622",
  "name": "Second Block Classes Begin",
  "date": "2024-10-19T00:00:00Z",
  "category": "Academic Deadlines",
  "location": "Online Event",
  "building": "online event",
  "image": "https://static7.campusgroups.com/upload/byui/2023/r2_image_upload_3997750_academicdeadline_002_891078.png",
  "rsvp": "/rsvp_boot?id=1932622",
  "info": "Second Block Classes Begin. Wed Oct 19 2024 12 AM. Online Event."
},
{
  "id": "1932623",
  "name": "Pay Deadline: Tuition/Health Plan - 2nd Block",
  "date": "2024-10-19T00:00:00Z",
  "category": "Financial Deadlines",
  "location": "Online Event",
  "building": "online event",
  "image": "https://static7.campusgroups.com/upload/byui/2023/r2_image_upload_1370220_financialdeadline_8818408.png",
  "rsvp": "/rsvp_boot?id=1932623",
  "info": "Pay Deadline: Tuition/Health Plan - 2nd Block. Wed Oct 19 2024 12 AM. Online Event."
},
{
  "id": "1933913",
  "name": "Red Cross Blood Drive",
  "date": "2024-10-19T10:00:00Z",
  "category": "Service",
  "location": "BYU-Idaho Center, Court 02",
  "building": "hart",
  "image": "https://static7.campusgroups.com/upload/byui/2023/r2_image_upload_1350379_armthatholdsheartordergivebloodblooddonationconceptsavinglives_68708763jpg_223151441.jpeg",
  "rsvp": "/rsvp_boot?id=1933913",
  "info": "Red Cross Blood Drive. Wed Oct 19 2024 10 AM. BYU-Idaho Center, Court 02."
},
{
  "id": "1940330",
  "name": "Brothers In Art: The Parsons",
  "date": "2024-10-19T10:00:00Z",
  "category": "Exhibit",
  "location": "Spori Art Gallery",
  "building": "spori",
  "image": "https://static7.campusgroups.com/upload/byui/2024/r2_image_upload_3997750_3d150f7072844c76838b387b30923f6fjpg_924133218.jpeg",
  "rsvp": "/rsvp_boot?id=1940330",
  "info": "Brothers In Art: The Parsons. Wed Oct 19 2024 10 AM. Spori Art Gallery."
},
{
  "id": "1940196",
  "name": "Crossroads Conversations - It is Well With My Soul: Redefining Wellness",
  "date": "2024-10-19T12:00:00Z",
  "category": "Involvement",
  "location": "Manwaring Center, 231B Crossroads Stage",
  "building": "manwaring",
  "image": "https://static7.campusgroups.com/upload/byui/2024/r2_image_upload_3997750_Crossroads_ConversationsIbelong_002_66184828.png",
  "rsvp": "/rsvp_boot?id=1940196",
  "info": "Crossroads Conversations - It is Well With My Soul: Redefining Wellness. Wed Oct 19 2024 12 PM. Manwaring Center, 231B Crossroads Stage."
},
{
  "id": "1939973",
  "name": "Wrestling Prep",
  "date": "2024-10-19T15:00:00Z",
  "category": "Sports",
  "location": "Hart, 187 Practice Room",
  "building": "hart",
  "image": "https://static7.campusgroups.com/upload/byui/2022/r2_image_upload_1350379_wrestling_728151539.jpeg",
  "rsvp": "/rsvp_boot?id=1939973",
  "info": "Wrestling Prep. Wed Oct 19 2024 3 PM. Hart, 187 Practice Room."
},
{
  "id": "1939013",
  "name": "Anxiety and Stress Workshop",
  "date": "2024-10-19T15:15:00Z",
  "category": "Meeting, Room Only",
  "location": "Manwaring Center, 176B Meeting Room",
  "building": "manwaring",
  "image": "https://static7.campusgroups.com/upload/byui/2024/r2_image_upload_3997750_Stress_and_anxiety__410125415.png",
  "rsvp": "/rsvp_boot?id=1939013",
  "info": "Anxiety and Stress Workshop. Wed Oct 19 2024 3:15 PM. Manwaring Center, 176B Meeting Room."
},
{
  "id": "1939001",
  "name": "Mental Health Empowerment Workshop",
  "date": "2024-10-19T16:00:00Z",
  "category": "Meeting, Room Only",
  "location": "Manwaring Center, 176B Meeting Room",
  "building": "manwaring",
  "image": "https://static7.campusgroups.com/upload/byui/2024/r2_image_upload_3997750_Copy_of_Mental_health_empowerment_workshop_Presentation_917191210.png",
  "rsvp": "/rsvp_boot?id=1939001",
  "info": "Mental Health Empowerment Workshop. Wed Oct 19 2024 4 PM. Manwaring Center, 176B Meeting Room."
},
{
  "id": "1939244",
  "name": "Fitess: Aerobics",
  "date": "2024-10-19T17:00:00Z",
  "category": "Fitness/Wellness",
  "location": "Hart, 234 Fitness Studio",
  "building": "hart",
  "image": "https://static7.campusgroups.com/upload/byui/2023/r2_image_upload_3997750_160929_FitnessClasses_015jpg_1219135940.jpeg",
  "rsvp": "/rsvp_boot?id=1939244",
  "info": "Fitess: Aerobics. Wed Oct 19 2024 5 PM. Hart, 234 Fitness Studio."
},
{
  "id": "1933635",
  "name": "Special Needs - Halloween Party",
  "date": "2024-10-19T18:00:00Z",
  "category": "Service",
  "location": "Hinckley, 260/270 Gym",
  "building": "hinckley",
  "image": "https://static7.campusgroups.com/upload/byui/2023/r2_image_upload_3997750_211022_specialneedshalloween_119jpg_1012114255.jpeg",
  "rsvp": "/rsvp_boot?id=1933635",
  "info": "Special Needs - Halloween Party. Wed Oct 19 2024 6 PM. Hinckley, 260/270 Gym."
},
{
  "id": "1939114",
  "name": "Fitness: Cross Training",
  "date": "2024-10-19T18:00:00Z",
  "category": "Fitness/Wellness",
  "location": "Hart, 182 Cross-Training",
  "building": "hart",
  "image": "https://static7.campusgroups.com/upload/byui/2023/r2_image_upload_3997750_230614_Cross_Fit_traning_090jpg_1219132419.jpeg",
  "rsvp": "/rsvp_boot?id=1939114",
  "info": "Fitness: Cross Training. Wed Oct 19 2024 6 PM. Hart, 182 Cross-Training."
},
{
  "id": "1939175",
  "name": "Fitness: Step",
  "date": "2024-10-19T18:00:00Z",
  "category": "Fitness/Wellness",
  "location": "Hart, 234 Fitness Studio",
  "building": "hart",
  "image": "https://static7.campusgroups.com/upload/byui/2022/r2_image_upload_1350379_stepjpg_831125733.jpeg",
  "rsvp": "/rsvp_boot?id=1939175",
  "info": "Fitness: Step. Wed Oct 19 2024 6 PM. Hart, 234 Fitness Studio."
},
{
  "id": "1939579",
  "name": "Pool/Billiards Sports Group",
  "date": "2024-10-19T18:00:00Z",
  "category": "Sports",
  "location": "Manwaring Center Crossroads Pool Tables",
  "building": "manwaring",
  "image": "https://static7.campusgroups.com/upload/byui/2024/r2_image_upload_3997750_Pool_Billiards_Sports_Group_002_909641.png",
  "rsvp": "/rsvp_boot?id=1939579",
  "info": "Pool/Billiards Sports Group. Wed Oct 19 2024 6 PM. Manwaring Center Crossroads Pool Tables."
},
{
  "id": "1933733",
  "name": "A New Perspective on Mindfulness",
  "date": "2024-10-19T19:00:00Z",
  "category": "Involvement",
  "location": "Manwaring Center, 176B Meeting Room",
  "building": "manwaring center",
  "image": "https://static7.campusgroups.com/upload/byui/2023/r2_image_upload_3997750_A_New_Perspective_on_Mindfulness_002_213748272.png",
  "rsvp": "/rsvp_boot?id=1933733",
  "info": "A New Perspective on Mindfulness. Wed Oct 19 2024 7 PM. Manwaring Center, 176B Meeting Room."
},
{
  "id": "1939838",
  "name": "Halloween Dance Party",
  "date": "2024-10-19T21:00:00Z",
  "category": "Dance",
  "location": "Manwaring Center, Crossroads Stage",
  "building": "manwaring",
  "image": "https://static7.campusgroups.com/upload/byui/2024/r2_image_upload_3997750_Halloween_Dance_Party_002_13142214.png",
  "rsvp": "/rsvp_boot?id=1939838",
  "info": "Halloween Dance Party. Wed Oct 19 2024 9 PM. Manwaring Center, Crossroads Stage."
}
]


